kegland_rapt_api_client/__init__.py
kegland_rapt_api_client/__main__.py
kegland_rapt_api_client/client.py
kegland_rapt_api_client-1.0.0.dist-info/LICENSE
kegland_rapt_api_client-1.0.0.dist-info/METADATA
kegland_rapt_api_client-1.0.0.dist-info/WHEEL
kegland_rapt_api_client-1.0.0.dist-info/entry_points.txt
kegland_rapt_api_client-1.0.0.dist-info/top_level.txt
kegland_rapt_api_client-1.0.0.dist-info/RECORD
