Metadata-Version: 2.1
Name: kegland-rapt-api-client
Version: 1.0.0
Summary: Client library written in Python for using Kegland RAPT's API
Author-email: Franta kolacek <work@kolacek.it>
License: MIT License
Project-URL: Homepage, https://github.com/fkolacek/kegland_rapt_api_client
Keywords: kegland,rapt,api
Classifier: License :: OSI Approved :: MIT License
Classifier: Programming Language :: Python
Classifier: Programming Language :: Python :: 3
Requires-Python: >=3.9
License-File: LICENSE
Requires-Dist: requests
Provides-Extra: dev
Requires-Dist: black ; extra == 'dev'
Requires-Dist: bumpver ; extra == 'dev'
Requires-Dist: isort ; extra == 'dev'
Requires-Dist: pip-tools ; extra == 'dev'
Requires-Dist: pytest ; extra == 'dev'
